EANOMAD/__init__.py
EANOMAD/core.py
EANOMAD/__pycache__/__init__.cpython-310.pyc
EANOMAD/__pycache__/__init__.cpython-312.pyc
EANOMAD/__pycache__/core.cpython-310.pyc
EANOMAD/__pycache__/core.cpython-312.pyc
eanomad-0.1.1.post8.dist-info/licenses/LICENSE
eanomad-0.1.1.post8.dist-info/METADATA
eanomad-0.1.1.post8.dist-info/WHEEL
eanomad-0.1.1.post8.dist-info/top_level.txt
eanomad-0.1.1.post8.dist-info/RECORD
