Metadata-Version: 2.4
Name: EANOMAD
Version: 0.1.1.post8
Summary: Evolutionary optimizer with NOMAD local search
Author-email: Miles Churchland <mileschurchand@gmail.com>
License: MIT License
Project-URL: Source, https://github.com/greenfire0/EANOMAD
Requires-Python: >=3.9
License-File: LICENSE
Requires-Dist: numpy>=1.23
Requires-Dist: tqdm>=4.66
Requires-Dist: pynomadbbo>=4
Provides-Extra: ray
Requires-Dist: ray>=2.10; extra == "ray"
Dynamic: license-file
